pybase_db/__init__.py
pybase_db/pybase_db.py
pybase_db/pysql.py
pybase_db-0.5.0.dist-info/LICENSE
pybase_db-0.5.0.dist-info/METADATA
pybase_db-0.5.0.dist-info/WHEEL
pybase_db-0.5.0.dist-info/top_level.txt
pybase_db-0.5.0.dist-info/RECORD
