Metadata-Version: 2.1
Name: pybase-db
Version: 0.5.0
Summary: PyBase is a database manager for multiple filetypes including SQLite3. Very poweful, simple and effective.
Home-page: http://ntbbloodbath.github.io/PyBase/
Author: NTBBloodbath
Author-email: bloodbathalchemist@protonmail.com
License: MIT
Platform: UNKNOWN
Classifier: Programming Language :: Python :: 3
Classifier: Programming Language :: Python :: 3.6
Classifier: Programming Language :: Python :: 3.7
Classifier: Programming Language :: Python :: 3.8
Classifier: Programming Language :: Python :: 3.9
Classifier: Development Status :: 4 - Beta
Classifier: Environment :: Console
Classifier: Intended Audience :: Developers
Classifier: License :: OSI Approved :: MIT License
Classifier: Operating System :: OS Independent
Classifier: Topic :: Database
Classifier: Topic :: Database :: Database Engines/Servers
Classifier: Topic :: Software Development :: Libraries
Requires-Dist: pyyaml (>=5.3.1)
Requires-Dist: rich (>=9.2.0)
